odrivein/__init__.py
odrivein/motor.py
odrivein/odrivein.py
odrivein-0.1.0.dist-info/LICENSE
odrivein-0.1.0.dist-info/METADATA
odrivein-0.1.0.dist-info/WHEEL
odrivein-0.1.0.dist-info/top_level.txt
odrivein-0.1.0.dist-info/RECORD
