Metadata-Version: 2.1
Name: odrivein
Version: 0.1.0
Summary: Easier and more user friendly interface to the Odrive
Author: Jouke de Jong
Author-email: jouke@stil-technology.com
Requires-Python: >=3.9
License-File: LICENSE
Requires-Dist: odrive==0.6.9_post0
